{
    "__class__": "TemplateAdversary", 
    "__module__": "loader.templates.TemplateAdversary", 
    "_base_threat": 1, 
    "_behaviors": [
        {
            "__class__": "BehaviorAttackMelee", 
            "__module__": "entity.actor.behaviors.BehaviorAttackMelee", 
            "_move_cost": 1, 
            "_strength": 5
        }, 
        {
            "__class__": "BehaviorMoveStupid", 
            "__module__": "entity.actor.behaviors.BehaviorMoveStupid", 
            "_move_cost": 1
        }
    ], 
    "_entity_name": "Cave Monster", 
    "_faction": {
        "__class__": "Faction", 
        "__module__": "entity.actor.Faction", 
        "_name": "Cave Monsters", 
        "_names_friendly_to": [], 
        "_names_hostile_to": [
            "Player", 
            "Robots"
        ], 
        "_names_neutral_to": []
    }, 
    "_image_name": "tortise.png", 
    "_max_hp": 100, 
    "_max_moves": 1, 
    "_rank": 3, 
    "_senses": [
        {
            "__class__": "SenseSight", 
            "__module__": "entity.actor.senses.SenseSight", 
            "_range": 9
        }
    ], 
    "_tools": null
}